cli/__init__.py
cli/main.py
cli/templates/__init__.py
cli/templates/manager.py
src/__init__.py
src/__main__.py
src/app.py
src/cli.py
src/config.py
src/main.py
src/events/__init__.py
src/health/__init__.py
src/health/router.py
src/helpers/__init__.py
src/helpers/mailer.py
src/helpers/storage.py
src/tasks/__init__.py
src/tasks/celery_app.py
src/tasks/email_tasks.py
src/tasks/example_tasks.py
src/tasks/router.py
src/utils/__init__.py
src/utils/error_handler.py
src/utils/password.py
src/utils/utils.py
src/utils/validators.py
yitech_fastapi-0.3.0.dist-info/METADATA
yitech_fastapi-0.3.0.dist-info/WHEEL
yitech_fastapi-0.3.0.dist-info/entry_points.txt
yitech_fastapi-0.3.0.dist-info/top_level.txt
yitech_fastapi-0.3.0.dist-info/RECORD
