Metadata-Version: 2.4
Name: yitech-fastapi
Version: 0.3.0
Summary: Add your description here
Author: Yitech Team
Author-email: contact@yitech.io
Requires-Python: >=3.12
Requires-Dist: yitool==0.6.0
Requires-Dist: slowapi==0.1.9
Requires-Dist: limits==3.11.0
Requires-Dist: click
Dynamic: author
Dynamic: author-email
Dynamic: requires-python
